holly.py
holly-2.0.0.dist-info/METADATA
holly-2.0.0.dist-info/WHEEL
holly-2.0.0.dist-info/top_level.txt
holly-2.0.0.dist-info/RECORD
